TempoMail/__init__.py
TempoMail/client.py
TempoMail/core.py
TempoMail/types/Account.py
TempoMail/types/Message.py
TempoMail/types/__init__.py
TempoMail-1.5.0.dist-info/LICENSE
TempoMail-1.5.0.dist-info/METADATA
TempoMail-1.5.0.dist-info/WHEEL
TempoMail-1.5.0.dist-info/top_level.txt
TempoMail-1.5.0.dist-info/RECORD
